deltakit_decode/__init__.py
deltakit_decode/_abstract_matching_decoders.py
deltakit_decode/_base_reporter.py
deltakit_decode/_mwpm_decoder.py
deltakit_decode/py.typed
deltakit_decode/analysis/__init__.py
deltakit_decode/analysis/_decoder_manager.py
deltakit_decode/analysis/_decoding_circuits.py
deltakit_decode/analysis/_empirical_decoding_error_distribution.py
deltakit_decode/analysis/_matching_decoder_managers.py
deltakit_decode/analysis/_run_all_analysis_engine.py
deltakit_decode/noise_sources/__init__.py
deltakit_decode/noise_sources/_generic_noise_sources.py
deltakit_decode/noise_sources/_matching_noise_sources.py
deltakit_decode/noise_sources/_stim_noise_sources.py
deltakit_decode/utils/__init__.py
deltakit_decode/utils/_decoding_graph_visualiser.py
deltakit_decode/utils/_derivation_tools.py
deltakit_decode/utils/_derivation_tools_pij.py
deltakit_decode/utils/_graph_circuit_helpers.py
deltakit_decode/utils/_log_utils.py
deltakit_decode/utils/_pij_visualiser.py
deltakit_decode-0.6.2.dist-info/licenses/LICENSE
deltakit_decode-0.6.2.dist-info/METADATA
deltakit_decode-0.6.2.dist-info/WHEEL
deltakit_decode-0.6.2.dist-info/top_level.txt
deltakit_decode-0.6.2.dist-info/RECORD
