Metadata-Version: 2.4
Name: deltakit-decode
Version: 0.6.2
Summary: Deltakit (component deltakit-decode)
Author-email: Deltakit Team <deltakit@riverlane.com>
License-Expression: Apache-2.0
Project-URL: Homepage, https://github.com/Deltakit/deltakit
Project-URL: Source, https://github.com/Deltakit/deltakit
Project-URL: Documentation, https://deltakit.riverlane.com/
Project-URL: Issues, https://github.com/Deltakit/deltakit/issues
Project-URL: Changelog, https://github.com/Deltakit/deltakit/releases
Classifier: Development Status :: 3 - Alpha
Classifier: Intended Audience :: Science/Research
Classifier: Intended Audience :: Developers
Classifier: Operating System :: OS Independent
Classifier: Programming Language :: Python
Classifier: Programming Language :: Python :: 3
Classifier: Programming Language :: Python :: 3 :: Only
Classifier: Programming Language :: Python :: 3.10
Classifier: Programming Language :: Python :: 3.11
Classifier: Programming Language :: Python :: 3.12
Classifier: Programming Language :: Python :: 3.13
Classifier: Programming Language :: Python :: Implementation :: CPython
Classifier: Topic :: Scientific/Engineering
Classifier: Topic :: Scientific/Engineering :: Quantum Computing
Classifier: Typing :: Typed
Requires-Python: <3.14,>=3.10
License-File: LICENSE
Requires-Dist: deltakit-circuit~=0.6
Requires-Dist: deltakit-core~=0.6
Requires-Dist: numpy>=1.26
Requires-Dist: networkx~=3.1
Requires-Dist: seaborn~=0.12
Requires-Dist: matplotlib~=3.5
Requires-Dist: plotly~=6.5
Requires-Dist: pymatching~=2.2
Requires-Dist: pymatching>=2.2.2,~=2.2; python_version >= "3.13"
Requires-Dist: stim~=1.11; python_version >= "3.10" and python_version < "3.12"
Requires-Dist: stim~=1.13; python_version >= "3.12" and python_version < "3.13"
Requires-Dist: stim~=1.15; python_version >= "3.13"
Requires-Dist: pathos~=0.3
Requires-Dist: pandas>=2.2.2
Requires-Dist: pandas~=2.3; python_version >= "3.13"
Requires-Dist: typing-extensions~=4.0
Requires-Dist: tqdm~=4.66
Dynamic: license-file
